{"description":"LibreBase connects your QardioBase smart scale straight to Apple Health — no account, no cloud, no Qardio app required.\n\nWhen Qardio shut down, the scales kept working over Bluetooth. LibreBase is a tiny, independent app that pairs with your scale, reads your weight the moment you step on, and saves it to Apple Health. Your data stays on your device.\n\nFEATURES\n• Direct Bluetooth connection to the QardioBase — works without the discontinued Qardio app\n• Automatic weigh-in: step on, and your weight is captured and saved to Apple Health\n• In-app BMI, calculated from your height and synced with Apple Health\n• Metric or imperial — kilograms/pounds and centimeters/feet follow your region\n• Battery and connection status at a glance, with one-tap reconnect\n• No accounts, no servers, no tracking\n\nCOMPATIBILITY\nLibreBase has so far been tested only with the original QardioBase (1st generation). QardioBase 2 and QardioBase X are not yet verified — they may work, but are untested. If you have another Qardio Base model, please try LibreBase and email librebaseapp@michelstorms.dev to tell us how it went — your reports help us support more scales, and we'll do our best to help with yours.\n\nLibreBase is open source. It is a wellness logger, not a medical device.\n\nTerms of Use: https://www.apple.com/legal/internet-services/itunes/dev/stdeula/","keywords":"qardio,scale,weight,smart scale,bmi,health,bluetooth,weigh,body weight,fitness,tracker","marketingUrl":"https://michelstorms.com/librebase/","promotionalText":"Your QardioBase lives on. LibreBase reads your weight over Bluetooth and saves it straight to Apple Health — no Qardio account, no cloud, no tracking.","supportUrl":"https://github.com/stormychel/LibreBase"}